odoo/addons/hr_job_category/README.rst
odoo/addons/hr_job_category/__init__.py
odoo/addons/hr_job_category/__manifest__.py
odoo/addons/hr_job_category/i18n/de.po
odoo/addons/hr_job_category/i18n/es.po
odoo/addons/hr_job_category/i18n/fi.po
odoo/addons/hr_job_category/i18n/fr.po
odoo/addons/hr_job_category/i18n/hr_job_category.pot
odoo/addons/hr_job_category/i18n/it.po
odoo/addons/hr_job_category/i18n/pt_BR.po
odoo/addons/hr_job_category/i18n/ro.po
odoo/addons/hr_job_category/i18n/sl.po
odoo/addons/hr_job_category/models/__init__.py
odoo/addons/hr_job_category/models/hr.py
odoo/addons/hr_job_category/readme/CONTRIBUTORS.md
odoo/addons/hr_job_category/readme/DESCRIPTION.md
odoo/addons/hr_job_category/readme/USAGE.md
odoo/addons/hr_job_category/static/description/icon.png
odoo/addons/hr_job_category/static/description/index.html
odoo/addons/hr_job_category/tests/__init__.py
odoo/addons/hr_job_category/tests/test_hr_job_categories.py
odoo/addons/hr_job_category/views/hr_view.xml
odoo_addon_hr_job_category-17.0.1.0.1.5.dist-info/METADATA
odoo_addon_hr_job_category-17.0.1.0.1.5.dist-info/WHEEL
odoo_addon_hr_job_category-17.0.1.0.1.5.dist-info/top_level.txt
odoo_addon_hr_job_category-17.0.1.0.1.5.dist-info/RECORD
