Metadata-Version: 2.1
Name: odoo-addon-hr_job_category
Version: 17.0.1.0.1.5
Requires-Python: >=3.10
Requires-Dist: odoo>=17.0a,<17.1dev
Summary: Adds tags to employee through contract and job position
Home-page: https://github.com/OCA/hr
License: AGPL-3
Author: Michael Telahun Makonnen <mmakonnen@gmail.com>, Savoir-faire Linux, Fekete Mihai (FBSR), Odoo Community Association (OCA)
Author-email: support@odoo-community.org
Classifier: Programming Language :: Python
Classifier: Framework :: Odoo
Classifier: Framework :: Odoo :: 17.0
Classifier: License :: OSI Approved :: GNU Affero General Public License v3
